<annotation>
	<folder>img</folder>
	<filename>image138.jpg</filename>
	<path>C:\Users\dlope\Desktop\img\image138.jpg</path>
	<source>
		<database>Unknown</database>
	</source>
	<size>
		<width>512</width>
		<height>512</height>
		<depth>3</depth>
	</size>
	<segmented>0</segmented>
	<object>
		<name>pinza</name>
		<pose>Unspecified</pose>
		<truncated>0</truncated>
		<difficult>0</difficult>
		<bndbox>
			<xmin>70</xmin>
			<ymin>216</ymin>
			<xmax>173</xmax>
			<ymax>311</ymax>
		</bndbox>
	</object>
	<object>
		<name>pinza</name>
		<pose>Unspecified</pose>
		<truncated>0</truncated>
		<difficult>0</difficult>
		<bndbox>
			<xmin>268</xmin>
			<ymin>325</ymin>
			<xmax>312</xmax>
			<ymax>382</ymax>
		</bndbox>
	</object>
</annotation>
