<annotation>
	<folder>img</folder>
	<filename>image144.jpg</filename>
	<path>C:\Users\dlope\Desktop\img\image144.jpg</path>
	<source>
		<database>Unknown</database>
	</source>
	<size>
		<width>512</width>
		<height>512</height>
		<depth>3</depth>
	</size>
	<segmented>0</segmented>
	<object>
		<name>pinza</name>
		<pose>Unspecified</pose>
		<truncated>0</truncated>
		<difficult>0</difficult>
		<bndbox>
			<xmin>120</xmin>
			<ymin>135</ymin>
			<xmax>241</xmax>
			<ymax>199</ymax>
		</bndbox>
	</object>
	<object>
		<name>pinza</name>
		<pose>Unspecified</pose>
		<truncated>0</truncated>
		<difficult>0</difficult>
		<bndbox>
			<xmin>124</xmin>
			<ymin>344</ymin>
			<xmax>182</xmax>
			<ymax>374</ymax>
		</bndbox>
	</object>
</annotation>
